trio/__init__.py
trio/__main__.py
trio/_abc.py
trio/_channel.py
trio/_deprecate.py
trio/_dtls.py
trio/_file_io.py
trio/_highlevel_generic.py
trio/_highlevel_open_tcp_listeners.py
trio/_highlevel_open_tcp_stream.py
trio/_highlevel_open_unix_stream.py
trio/_highlevel_serve_listeners.py
trio/_highlevel_socket.py
trio/_highlevel_ssl_helpers.py
trio/_path.py
trio/_repl.py
trio/_signals.py
trio/_socket.py
trio/_ssl.py
trio/_subprocess.py
trio/_sync.py
trio/_threads.py
trio/_timeouts.py
trio/_unix_pipes.py
trio/_util.py
trio/_version.py
trio/_wait_for_object.py
trio/_windows_pipes.py
trio/abc.py
trio/from_thread.py
trio/lowlevel.py
trio/py.typed
trio/socket.py
trio/to_thread.py
trio/_core/__init__.py
trio/_core/_asyncgens.py
trio/_core/_concat_tb.py
trio/_core/_entry_queue.py
trio/_core/_exceptions.py
trio/_core/_generated_instrumentation.py
trio/_core/_generated_io_epoll.py
trio/_core/_generated_io_kqueue.py
trio/_core/_generated_io_windows.py
trio/_core/_generated_run.py
trio/_core/_instrumentation.py
trio/_core/_io_common.py
trio/_core/_io_epoll.py
trio/_core/_io_kqueue.py
trio/_core/_io_windows.py
trio/_core/_ki.py
trio/_core/_local.py
trio/_core/_mock_clock.py
trio/_core/_parking_lot.py
trio/_core/_run.py
trio/_core/_thread_cache.py
trio/_core/_traps.py
trio/_core/_unbounded_queue.py
trio/_core/_wakeup_socketpair.py
trio/_core/_windows_cffi.py
trio/_core/_tests/__init__.py
trio/_core/_tests/test_asyncgen.py
trio/_core/_tests/test_exceptiongroup_gc.py
trio/_core/_tests/test_guest_mode.py
trio/_core/_tests/test_instrumentation.py
trio/_core/_tests/test_io.py
trio/_core/_tests/test_ki.py
trio/_core/_tests/test_local.py
trio/_core/_tests/test_mock_clock.py
trio/_core/_tests/test_parking_lot.py
trio/_core/_tests/test_run.py
trio/_core/_tests/test_thread_cache.py
trio/_core/_tests/test_tutil.py
trio/_core/_tests/test_unbounded_queue.py
trio/_core/_tests/test_windows.py
trio/_core/_tests/tutil.py
trio/_core/_tests/type_tests/nursery_start.py
trio-0.26.1.dist-info/LICENSE
trio-0.26.1.dist-info/LICENSE.APACHE2
trio-0.26.1.dist-info/LICENSE.MIT
trio-0.26.1.dist-info/METADATA
trio-0.26.1.dist-info/WHEEL
trio-0.26.1.dist-info/entry_points.txt
trio-0.26.1.dist-info/top_level.txt
trio-0.26.1.dist-info/RECORD
