Metadata-Version: 2.1
Name: trio
Version: 0.26.1
Summary: A friendly Python library for async concurrency and I/O
Author-email: "Nathaniel J. Smith" <njs@pobox.com>
License: MIT OR Apache-2.0
Project-URL: Homepage, https://github.com/python-trio/trio
Project-URL: Documentation, https://trio.readthedocs.io/
Project-URL: Changelog, https://trio.readthedocs.io/en/latest/history.html
Keywords: async,io,networking,trio
Classifier: Development Status :: 3 - Alpha
Classifier: Framework :: Trio
Classifier: Intended Audience :: Developers
Classifier: License :: OSI Approved :: MIT License
Classifier: License :: OSI Approved :: Apache Software License
Classifier: Operating System :: POSIX :: Linux
Classifier: Operating System :: MacOS :: MacOS X
Classifier: Operating System :: POSIX :: BSD
Classifier: Operating System :: Microsoft :: Windows
Classifier: Programming Language :: Python :: Implementation :: CPython
Classifier: Programming Language :: Python :: Implementation :: PyPy
Classifier: Programming Language :: Python :: 3 :: Only
Classifier: Programming Language :: Python :: 3.8
Classifier: Programming Language :: Python :: 3.9
Classifier: Programming Language :: Python :: 3.10
Classifier: Programming Language :: Python :: 3.11
Classifier: Programming Language :: Python :: 3.12
Classifier: Programming Language :: Python :: 3.13
Classifier: Topic :: System :: Networking
Classifier: Typing :: Typed
Requires-Python: >=3.8
License-File: LICENSE
License-File: LICENSE.APACHE2
License-File: LICENSE.MIT
Requires-Dist: attrs>=23.2.0
Requires-Dist: sortedcontainers
Requires-Dist: idna
Requires-Dist: outcome
Requires-Dist: sniffio>=1.3.0
Requires-Dist: cffi>=1.14; os_name == "nt" and implementation_name != "pypy"
Requires-Dist: exceptiongroup; python_version < "3.11"
